xiuxian_work/__init__.py
xiuxian_work/reward_data_source.py
xiuxian_work/work_handle.py
xiuxian_work/workmake.py
xiuxian_work-0.30.dist-info/METADATA
xiuxian_work-0.30.dist-info/WHEEL
xiuxian_work-0.30.dist-info/top_level.txt
xiuxian_work-0.30.dist-info/RECORD
